AUTHORS.rst
CONTRIBUTING.rst
HISTORY.rst
LICENSE
MANIFEST.in
README.rst
setup.py
authstrap/__init__.py
authstrap/models.py
authstrap/urls.py
authstrap/static/js/authstrap.js
authstrap/templates/authstrap/base.html
authstrap/templates/authstrap/base_auth.html
authstrap/templates/authstrap/login.html
authstrap/templates/authstrap/logout.html
authstrap/templates/authstrap/password_change_done.html
authstrap/templates/authstrap/password_change_form.html
authstrap/templates/authstrap/password_reset_complete.html
authstrap/templates/authstrap/password_reset_confirm.html
authstrap/templates/authstrap/password_reset_done.html
authstrap/templates/authstrap/password_reset_email.html
authstrap/templates/authstrap/password_reset_form.html
django_authstrap.egg-info/PKG-INFO
django_authstrap.egg-info/SOURCES.txt
django_authstrap.egg-info/dependency_links.txt
django_authstrap.egg-info/not-zip-safe
django_authstrap.egg-info/requires.txt
django_authstrap.egg-info/top_level.txt