Metadata-Version: 1.0
Name: django-authstrap
Version: 0.2.2
Summary: Bootstrap templates for django.contrib.auth
Home-page: https://github.com/alixedi/django_authstrap
Author: Ali Zaidi
Author-email: alixedi@gmail.com
License: BSD
Keywords: django_authstrap
Platform: UNKNOWN
Classifier: Development Status :: 2 - Pre-Alpha
Classifier: Framework :: Django
Classifier: Intended Audience :: Developers
Classifier: License :: OSI Approved :: BSD License
Classifier: Natural Language :: English
Classifier: Programming Language :: Python :: 2
Classifier: Programming Language :: Python :: 2.6
Classifier: Programming Language :: Python :: 2.7
Classifier: Programming Language :: Python :: 3
Classifier: Programming Language :: Python :: 3.3
